yabf/__init__.py
yabf/chi2.py
yabf/cli.py
yabf/core/__init__.py
yabf/core/component.py
yabf/core/configio.py
yabf/core/io.py
yabf/core/likelihood.py
yabf/core/mpi.py
yabf/core/parameters.py
yabf/core/plugin.py
yabf/core/samplers.py
yabf/core/typing.py
yabf/core/utils.py
yabf/samplers/__init__.py
yabf/samplers/emcee.py
yabf/samplers/polychord.py
yabf-2.1.1.dist-info/LICENSE.rst
yabf-2.1.1.dist-info/METADATA
yabf-2.1.1.dist-info/WHEEL
yabf-2.1.1.dist-info/entry_points.txt
yabf-2.1.1.dist-info/top_level.txt
yabf-2.1.1.dist-info/RECORD
