Metadata-Version: 2.1
Name: yabf
Version: 2.1.1
Summary: Yet Another Bayesian Framework
Home-page: https://github.com/steven-murray/yabf
Author: Steven Murray
Author-email: steven.g.murray@asu.edu
License: MIT
Project-URL: Documentation, https://yabf.readthedocs.org
Platform: any
Classifier: Development Status :: 2 - Pre-Alpha
Classifier: Intended Audience :: Science/Research
Classifier: License :: OSI Approved
Classifier: License :: OSI Approved :: MIT License
Classifier: Natural Language :: English
Classifier: Programming Language :: Python :: 3
Classifier: Programming Language :: Python :: 3 :: Only
Classifier: Programming Language :: Python :: 3.8
Classifier: Programming Language :: Python :: 3.9
Classifier: Programming Language :: Python :: 3.10
Classifier: Programming Language :: Python :: Implementation :: CPython
Classifier: Topic :: Scientific/Engineering :: Astronomy
Classifier: Topic :: Scientific/Engineering :: Physics
Requires-Python: >=3.8
License-File: LICENSE.rst
Requires-Dist: cached-property
Requires-Dist: click (>=6.0)
Requires-Dist: frozendict
Requires-Dist: getdist
Requires-Dist: numpy (>=1.6.2)
Requires-Dist: pyyaml (>=5)
Requires-Dist: rich
Requires-Dist: scipy (>=1.0.0)
Requires-Dist: importlib-metadata ; python_version < "3.8"
Provides-Extra: dev
Requires-Dist: Sphinx (>=1.7.5) ; extra == 'dev'
Requires-Dist: bump2version ; extra == 'dev'
Requires-Dist: coverage (>=4.5.1) ; extra == 'dev'
Requires-Dist: nbsphinx ; extra == 'dev'
Requires-Dist: numpydoc (>=0.8.0) ; extra == 'dev'
Requires-Dist: pre-commit ; extra == 'dev'
Requires-Dist: pytest (>=3.5.1) ; extra == 'dev'
Requires-Dist: pytest-cov (>=2.5.1) ; extra == 'dev'
Requires-Dist: pytest-lazy-fixture ; extra == 'dev'
Provides-Extra: docs
Requires-Dist: Sphinx (>=1.7.5) ; extra == 'docs'
Requires-Dist: nbsphinx ; extra == 'docs'
Requires-Dist: numpydoc (>=0.8.0) ; extra == 'docs'
Provides-Extra: tests
Requires-Dist: coverage (>=4.5.1) ; extra == 'tests'
Requires-Dist: pre-commit ; extra == 'tests'
Requires-Dist: pytest (>=3.5.1) ; extra == 'tests'
Requires-Dist: pytest-cov (>=2.5.1) ; extra == 'tests'
Requires-Dist: pytest-lazy-fixture ; extra == 'tests'
